csv2opd/__init__.py
csv2opd/csv2opd.py
csv2opd-1.1.1.dist-info/LICENSE
csv2opd-1.1.1.dist-info/METADATA
csv2opd-1.1.1.dist-info/WHEEL
csv2opd-1.1.1.dist-info/entry_points.txt
csv2opd-1.1.1.dist-info/top_level.txt
csv2opd-1.1.1.dist-info/RECORD
