Metadata-Version: 2.1
Name: csv2opd
Version: 1.1.1
Summary: A CSV to XML converter for OpenProdoc
Home-page: https://github.com/guillearch/csv2opd
Author: Guillermo Castellano
Author-email: gcastellano@protonmail.com
License: UNKNOWN
Platform: UNKNOWN
Classifier: Programming Language :: Python :: 3
Classifier: License :: OSI Approved :: GNU General Public License v3 (GPLv3)
Classifier: Operating System :: OS Independent
